pyrobud/__init__.py
pyrobud/__main__.py
pyrobud/command.py
pyrobud/core/__init__.py
pyrobud/core/bot.py
pyrobud/core/bot_mixin_base.py
pyrobud/core/command_dispatcher.py
pyrobud/core/database_provider.py
pyrobud/core/event_dispatcher.py
pyrobud/core/module_extender.py
pyrobud/core/telegram_bot.py
pyrobud/custom_modules/.gitignore
pyrobud/custom_modules/__init__.py
pyrobud/custom_modules/example.py
pyrobud/launch.py
pyrobud/listener.py
pyrobud/logs.py
pyrobud/main.py
pyrobud/module.py
pyrobud/modules/__init__.py
pyrobud/modules/antibot.py
pyrobud/modules/bot_setup.py
pyrobud/modules/core.py
pyrobud/modules/debug.py
pyrobud/modules/manager.py
pyrobud/modules/moderation.py
pyrobud/modules/network.py
pyrobud/modules/snippet.py
pyrobud/modules/stats.py
pyrobud/modules/sticker.py
pyrobud/modules/system.py
pyrobud/modules/text.py
pyrobud/util/__init__.py
pyrobud/util/async_helpers.py
pyrobud/util/config.py
pyrobud/util/config_db_migrator.py
pyrobud/util/db.py
pyrobud/util/error.py
pyrobud/util/git.py
pyrobud/util/image.py
pyrobud/util/misc.py
pyrobud/util/sentry.py
pyrobud/util/system.py
pyrobud/util/text.py
pyrobud/util/tg.py
pyrobud/util/time.py
pyrobud/util/version.py
pyrobud/version.py
pyrobud-2.1.0.dist-info/entry_points.txt
pyrobud-2.1.0.dist-info/LICENSE
pyrobud-2.1.0.dist-info/WHEEL
pyrobud-2.1.0.dist-info/METADATA
pyrobud-2.1.0.dist-info/RECORD
