Metadata-Version: 2.1
Name: pyrobud
Version: 2.1.0
Summary: A clean selfbot for Telegram with an emphasis on quality and practicality.
Home-page: https://github.com/kdrag0n/pyrobud
License: MIT
Keywords: chat,telegram,selfbot,telegram-bot,telethon
Author: Danny Lin
Author-email: danny@kdrag0n.dev
Requires-Python: >=3.6,<4.0
Classifier: Development Status :: 4 - Beta
Classifier: Environment :: Console
Classifier: Environment :: No Input/Output (Daemon)
Classifier: Framework :: AsyncIO
Classifier: Intended Audience :: End Users/Desktop
Classifier: License :: OSI Approved :: MIT License
Classifier: Operating System :: OS Independent
Classifier: Programming Language :: Python :: 3
Classifier: Programming Language :: Python :: 3.6
Classifier: Programming Language :: Python :: 3.7
Classifier: Programming Language :: Python :: 3.8
Classifier: Topic :: Communications
Classifier: Topic :: Communications :: Chat
Classifier: Topic :: Internet
Provides-Extra: fast
Requires-Dist: aiohttp (>=3.6.2,<4.0.0)
Requires-Dist: aiorun (>=2019.11.1,<2021.0.0)
Requires-Dist: beauty-print (>=0.6.0,<0.7.0)
Requires-Dist: colorlog (>=4.1.0,<5.0.0)
Requires-Dist: cryptg (>=0.2.post0,<0.3); extra == "fast"
Requires-Dist: emoji (>=0.5.4,<0.6.0)
Requires-Dist: gitpython (>=3.0.5,<4.0.0)
Requires-Dist: meval (>=2.5,<3.0)
Requires-Dist: msgpack (>=0.6.2,<1.1.0)
Requires-Dist: pillow (>=6.2.2,<8.0.0)
Requires-Dist: plyvel (>=1.1.0,<2.0.0)
Requires-Dist: ratelimit (>=2.2.1,<3.0.0)
Requires-Dist: sentry-sdk (>=0.13.5,<0.15.0)
Requires-Dist: speedtest-cli (>=2.1.2,<3.0.0)
Requires-Dist: telethon (>=1.10.10,<2.0.0)
Requires-Dist: tomlkit (>=0.5.8,<0.7.0)
Project-URL: Bug Tracker, https://github.com/kdrag0n/pyrobud/issues
Project-URL: Community, https://t.me/pyrobud
Project-URL: Documentation, https://github.com/kdrag0n/pyrobud/blob/master/README.md
Project-URL: Repository, https://github.com/kdrag0n/pyrobud
